helpfunc.py
helpfunc-1.0.1.dist-info/LICENSE
helpfunc-1.0.1.dist-info/METADATA
helpfunc-1.0.1.dist-info/WHEEL
helpfunc-1.0.1.dist-info/top_level.txt
helpfunc-1.0.1.dist-info/RECORD
