Metadata-Version: 2.1
Name: helpfunc
Version: 1.0.1
Summary: help function collection
Home-page: https://github.com/Yaphp/helpfunc
Author: Yaphp
Author-email: yaphp960907@gmail.com
License: MIT
Download-URL: https://github.com/Yaphp/helpfunc.git
Keywords: help,function,simple
Platform: UNKNOWN
Classifier: Programming Language :: Python :: 3
Classifier: License :: OSI Approved :: MIT License
Classifier: Operating System :: OS Independent
Requires-Python: >=3.6
